blackchirp/__init__.py
blackchirp/bcfid.py
blackchirp/bcftmw.py
blackchirp/bclif.py
blackchirp/blackchirpexperiment.py
blackchirp-0.0.5.dist-info/LICENSE
blackchirp-0.0.5.dist-info/METADATA
blackchirp-0.0.5.dist-info/WHEEL
blackchirp-0.0.5.dist-info/top_level.txt
blackchirp-0.0.5.dist-info/RECORD
