Metadata-Version: 2.1
Name: blackchirp
Version: 0.0.5
Summary: Python module for blackchirp: data acquisition software for CP-FTMW spectroscopy
Author-email: Kyle Crabtree <kncrabtree@ucdavis.edu>
License: MIT License
Classifier: License :: OSI Approved :: MIT License
Classifier: Programming Language :: Python :: 3
Requires-Python: >=3.9
License-File: LICENSE
Requires-Dist: numpy
Requires-Dist: pandas
Requires-Dist: scipy
